[
  {
    "id": 1784645702235,
    "nama": "Zahwa Alya putri",
    "kelas": "X.1 DIGITAL",
    "nohp": "+62 853-2000-7930",
    "mapel": "PJOK",
    "status": "Hadir",
    "jam": "21.55",
    "tgl": "21/7/2026",
    "petugas": "Razqa"
  },
  {
    "id": 1784645698289,
    "nama": "Khaira Sachi Kayana",
    "kelas": "X.1 DIGITAL",
    "nohp": "+62 821-7002-0056",
    "mapel": "PJOK",
    "status": "Hadir",
    "jam": "21.54",
    "tgl": "21/7/2026",
    "petugas": "Razqa"
  },
  {
    "id": 1784645694751,
    "nama": "Rivana Azzahra",
    "kelas": "X.1 DIGITAL",
    "nohp": "+62 812-2908-5724",
    "mapel": "PJOK",
    "status": "Hadir",
    "jam": "21.54",
    "tgl": "21/7/2026",
    "petugas": "Razqa"
  },
  {
    "id": 1784645691220,
    "nama": "Aimatul Chaira Syah",
    "kelas": "X.1 DIGITAL",
    "nohp": "+62 812-7709-1148",
    "mapel": "PJOK",
    "status": "Hadir",
    "jam": "21.54",
    "tgl": "21/7/2026",
    "petugas": "Razqa"
  },
  {
    "id": 1784645686722,
    "nama": "Fabyola Safitri",
    "kelas": "X.1 DIGITAL",
    "nohp": "+62 878-1154-6321",
    "mapel": "PJOK",
    "status": "Hadir",
    "jam": "21.54",
    "tgl": "21/7/2026",
    "petugas": "Razqa"
  },
  {
    "id": 1784645681959,
    "nama": "Farrel Alvaro Laksamana",
    "kelas": "X.1 DIGITAL",
    "nohp": "+62 877-1121-8213",
    "mapel": "PJOK",
    "status": "Hadir",
    "jam": "21.54",
    "tgl": "21/7/2026",
    "petugas": "Razqa"
  },
  {
    "id": 1784645676741,
    "nama": "Alika Kaysha Athalia",
    "kelas": "X.1 DIGITAL",
    "nohp": "+62 895-1857-9735",
    "mapel": "PJOK",
    "status": "Hadir",
    "jam": "21.54",
    "tgl": "21/7/2026",
    "petugas": "Razqa"
  },
  {
    "id": 1784645671888,
    "nama": "Muhammad Al Akram Boer",
    "kelas": "X.1 DIGITAL",
    "nohp": "+62 896-7941-8538",
    "mapel": "PJOK",
    "status": "Hadir",
    "jam": "21.54",
    "tgl": "21/7/2026",
    "petugas": "Razqa"
  },
  {
    "id": 1784645667506,
    "nama": "Sabrina Arif Rayyani",
    "kelas": "X.1 DIGITAL",
    "nohp": "+62 853-5501-9199",
    "mapel": "PJOK",
    "status": "Hadir",
    "jam": "21.54",
    "tgl": "21/7/2026",
    "petugas": "Razqa"
  },
  {
    "id": 1784645656242,
    "nama": "Luthfi Karim",
    "kelas": "X.1 DIGITAL",
    "nohp": "+62 822-8991-3571",
    "mapel": "PJOK",
    "status": "Hadir",
    "jam": "21.54",
    "tgl": "21/7/2026",
    "petugas": "Razqa"
  },
  {
    "id": 1784645650896,
    "nama": "Alicia Queenara",
    "kelas": "X.1 DIGITAL",
    "nohp": "+62 821-7089-9030",
    "mapel": "PJOK",
    "status": "Hadir",
    "jam": "21.54",
    "tgl": "21/7/2026",
    "petugas": "Razqa"
  }
]