[
  {
    "id": 1784600703909,
    "nama": "Rakha Dwinanda Putra",
    "kelas": "X.1 DIGITAL",
    "nohp": "+62 821-7152-8540",
    "mapel": "TIK",
    "status": "Hadir",
    "jam": "09.25",
    "tgl": "21/7/2026"
  },
  {
    "id": 1784600699771,
    "nama": "Alicia Queenara",
    "kelas": "X.1 DIGITAL",
    "nohp": "+62 821-7089-9030",
    "mapel": "TIK",
    "status": "Hadir",
    "jam": "09.24",
    "tgl": "21/7/2026"
  },
  {
    "id": 1784600696784,
    "nama": "Zahwa Alya putri",
    "kelas": "X.1 DIGITAL",
    "nohp": "+62 853-2000-7930",
    "mapel": "TIK",
    "status": "Hadir",
    "jam": "09.24",
    "tgl": "21/7/2026"
  },
  {
    "id": 1784600692599,
    "nama": "Darrell Yusuf Athila",
    "kelas": "X.1 DIGITAL",
    "nohp": "+62 812-6810-404",
    "mapel": "TIK",
    "status": "Hadir",
    "jam": "09.24",
    "tgl": "21/7/2026"
  },
  {
    "id": 1784600686396,
    "nama": "Synneva Adhwaretha",
    "kelas": "X.1 DIGITAL",
    "nohp": "+62 813-3442-3333",
    "mapel": "TIK",
    "status": "Hadir",
    "jam": "09.24",
    "tgl": "21/7/2026"
  },
  {
    "id": 1784600681904,
    "nama": "Rivana Azzahra",
    "kelas": "X.1 DIGITAL",
    "nohp": "+62 812-2908-5724",
    "mapel": "TIK",
    "status": "Hadir",
    "jam": "09.24",
    "tgl": "21/7/2026"
  },
  {
    "id": 1784600679046,
    "nama": "Karen Trirely Gita Simatupang",
    "kelas": "X.1 DIGITAL",
    "nohp": "+62 821-5997-0950",
    "mapel": "TIK",
    "status": "Hadir",
    "jam": "09.24",
    "tgl": "21/7/2026"
  },
  {
    "id": 1784600675278,
    "nama": "Rahma Andini Soraya",
    "kelas": "X.1 DIGITAL",
    "nohp": "+62 831-6113-9346",
    "mapel": "TIK",
    "status": "Hadir",
    "jam": "09.24",
    "tgl": "21/7/2026"
  },
  {
    "id": 1784600673255,
    "nama": "Jihan Afifah",
    "kelas": "X.1 DIGITAL",
    "nohp": "+62 895-3623-89300",
    "mapel": "TIK",
    "status": "Hadir",
    "jam": "09.24",
    "tgl": "21/7/2026"
  },
  {
    "id": 1784600665529,
    "nama": "Lakeysha Aura Rezki",
    "kelas": "X.1 DIGITAL",
    "nohp": "+62 812-7555-4776",
    "mapel": "TIK",
    "status": "Hadir",
    "jam": "09.24",
    "tgl": "21/7/2026"
  },
  {
    "id": 1784600662165,
    "nama": "Farrel Alvaro Laksamana",
    "kelas": "X.1 DIGITAL",
    "nohp": "+62 877-1121-8213",
    "mapel": "TIK",
    "status": "Hadir",
    "jam": "09.24",
    "tgl": "21/7/2026"
  },
  {
    "id": 1784600647610,
    "nama": "Aimatul Chaira Syah",
    "kelas": "X.1 DIGITAL",
    "nohp": "+62 812-7709-1148",
    "mapel": "TIK",
    "status": "Hadir",
    "jam": "09.24",
    "tgl": "21/7/2026"
  },
  {
    "id": 1784600627444,
    "nama": "Atika Najwa Ikhwani",
    "kelas": "X.1 DIGITAL",
    "nohp": "+62 877-0928-7343",
    "mapel": "TIK",
    "status": "Hadir",
    "jam": "09.23",
    "tgl": "21/7/2026"
  },
  {
    "id": 1784600622518,
    "nama": "Lailatul Salma",
    "kelas": "X.1 DIGITAL",
    "nohp": "+62 853-5501-8366",
    "mapel": "TIK",
    "status": "Hadir",
    "jam": "09.23",
    "tgl": "21/7/2026"
  },
  {
    "id": 1784600618553,
    "nama": "Sabrina Arif Rayyani",
    "kelas": "X.1 DIGITAL",
    "nohp": "+62 853-5501-9199",
    "mapel": "TIK",
    "status": "Hadir",
    "jam": "09.23",
    "tgl": "21/7/2026"
  },
  {
    "id": 1784600614022,
    "nama": "Arum Mustifa",
    "kelas": "X.1 DIGITAL",
    "nohp": "+62 831-8751-2604",
    "mapel": "TIK",
    "status": "Hadir",
    "jam": "09.23",
    "tgl": "21/7/2026"
  },
  {
    "id": 1784600605574,
    "nama": "Fabyola Safitri",
    "kelas": "X.1 DIGITAL",
    "nohp": "+62 878-1154-6321",
    "mapel": "TIK",
    "status": "Hadir",
    "jam": "09.23",
    "tgl": "21/7/2026"
  },
  {
    "id": 1784600597458,
    "nama": "Aulia Anisa Putri",
    "kelas": "X.1 DIGITAL",
    "nohp": "+62 838-2604-8596",
    "mapel": "TIK",
    "status": "Hadir",
    "jam": "09.23",
    "tgl": "21/7/2026"
  },
  {
    "id": 1784600594834,
    "nama": "Jamillatul Lathifah",
    "kelas": "X.1 DIGITAL",
    "nohp": "+62 821-7070-4249",
    "mapel": "TIK",
    "status": "Hadir",
    "jam": "09.23",
    "tgl": "21/7/2026"
  },
  {
    "id": 1784600588802,
    "nama": "Muhammad Ibnu Syabil",
    "kelas": "X.1 DIGITAL",
    "nohp": "+62 813-7884-8072",
    "mapel": "TIK",
    "status": "Hadir",
    "jam": "09.23",
    "tgl": "21/7/2026"
  },
  {
    "id": 1784600582883,
    "nama": "Zheno Alfares",
    "kelas": "X.1 DIGITAL",
    "nohp": "+62 822-8498-3746",
    "mapel": "TIK",
    "status": "Hadir",
    "jam": "09.23",
    "tgl": "21/7/2026"
  },
  {
    "id": 1784593465633,
    "nama": "Hakam Sadiq Pati",
    "kelas": "X.1 DIGITAL",
    "nohp": "-",
    "mapel": "B. INGGRIS & SASTRA",
    "status": "Hadir",
    "jam": "07.24",
    "tgl": "21/7/2026"
  },
  {
    "id": 1784593429805,
    "nama": "Razqa Fazil Defandryan Zack",
    "kelas": "X.1 DIGITAL",
    "nohp": "+48 666 666 672",
    "mapel": "B. INGGRIS & SASTRA",
    "status": "Hadir",
    "jam": "07.23",
    "tgl": "21/7/2026"
  },
  {
    "id": 1784593328912,
    "nama": "Farrel Alvaro Laksamana",
    "kelas": "X.1 DIGITAL",
    "nohp": "+62 877-1121-8213",
    "mapel": "PJOK",
    "status": "Hadir",
    "jam": "07.22",
    "tgl": "21/7/2026"
  },
  {
    "id": 1784593326503,
    "nama": "Jamillatul Lathifah",
    "kelas": "X.1 DIGITAL",
    "nohp": "+62 821-7070-4249",
    "mapel": "PJOK",
    "status": "Hadir",
    "jam": "07.22",
    "tgl": "21/7/2026"
  },
  {
    "id": 1784593323963,
    "nama": "Hakam Sadiq Pati",
    "kelas": "X.1 DIGITAL",
    "nohp": "-",
    "mapel": "PJOK",
    "status": "Hadir",
    "jam": "07.22",
    "tgl": "21/7/2026"
  },
  {
    "id": 1784593317729,
    "nama": "Khaira Sachi Kayana",
    "kelas": "X.1 DIGITAL",
    "nohp": "+62 821-7002-0056",
    "mapel": "PJOK",
    "status": "Hadir",
    "jam": "07.21",
    "tgl": "21/7/2026"
  },
  {
    "id": 1784593314917,
    "nama": "Luthfi Karim",
    "kelas": "X.1 DIGITAL",
    "nohp": "+62 822-8991-3571",
    "mapel": "PJOK",
    "status": "Hadir",
    "jam": "07.21",
    "tgl": "21/7/2026"
  },
  {
    "id": 1784593313005,
    "nama": "Rakha Dwinanda Putra",
    "kelas": "X.1 DIGITAL",
    "nohp": "+62 821-7152-8540",
    "mapel": "PJOK",
    "status": "Hadir",
    "jam": "07.21",
    "tgl": "21/7/2026"
  },
  {
    "id": 1784593311373,
    "nama": "Rahma Andini Soraya",
    "kelas": "X.1 DIGITAL",
    "nohp": "+62 831-6113-9346",
    "mapel": "PJOK",
    "status": "Hadir",
    "jam": "07.21",
    "tgl": "21/7/2026"
  },
  {
    "id": 1784593309446,
    "nama": "Rahmad Ghatfan",
    "kelas": "X.1 DIGITAL",
    "nohp": "+62 857-6330-4596",
    "mapel": "PJOK",
    "status": "Hadir",
    "jam": "07.21",
    "tgl": "21/7/2026"
  },
  {
    "id": 1784593304533,
    "nama": "Zheno Alfares",
    "kelas": "X.1 DIGITAL",
    "nohp": "+62 822-8498-3746",
    "mapel": "PJOK",
    "status": "Hadir",
    "jam": "07.21",
    "tgl": "21/7/2026"
  },
  {
    "id": 1784593299596,
    "nama": "Zahwa Alya putri",
    "kelas": "X.1 DIGITAL",
    "nohp": "+62 853-2000-7930",
    "mapel": "PJOK",
    "status": "Hadir",
    "jam": "07.21",
    "tgl": "21/7/2026"
  },
  {
    "id": 1784593293100,
    "nama": "Synneva Adhwaretha",
    "kelas": "X.1 DIGITAL",
    "nohp": "+62 813-3442-3333",
    "mapel": "PJOK",
    "status": "Hadir",
    "jam": "07.21",
    "tgl": "21/7/2026"
  },
  {
    "id": 1784593287196,
    "nama": "Sabrina Arif Rayyani",
    "kelas": "X.1 DIGITAL",
    "nohp": "+62 853-5501-9199",
    "mapel": "PJOK",
    "status": "Hadir",
    "jam": "07.21",
    "tgl": "21/7/2026"
  },
  {
    "id": 1784593282328,
    "nama": "Rivana Azzahra",
    "kelas": "X.1 DIGITAL",
    "nohp": "+62 812-2908-5724",
    "mapel": "PJOK",
    "status": "Hadir",
    "jam": "07.21",
    "tgl": "21/7/2026"
  },
  {
    "id": 1784593274361,
    "nama": "Muhammad Ibnu Syabil",
    "kelas": "X.1 DIGITAL",
    "nohp": "+62 813-7884-8072",
    "mapel": "PJOK",
    "status": "Hadir",
    "jam": "07.21",
    "tgl": "21/7/2026"
  },
  {
    "id": 1784593264516,
    "nama": "Muhammad Al Akram Boer",
    "kelas": "X.1 DIGITAL",
    "nohp": "+62 896-7941-8538",
    "mapel": "PJOK",
    "status": "Hadir",
    "jam": "07.21",
    "tgl": "21/7/2026"
  },
  {
    "id": 1784593261496,
    "nama": "Nashita Naura",
    "kelas": "X.1 DIGITAL",
    "nohp": "+62 812-7722-0850",
    "mapel": "PJOK",
    "status": "Hadir",
    "jam": "07.21",
    "tgl": "21/7/2026"
  },
  {
    "id": 1784593259655,
    "nama": "Lakeysha Aura Rezki",
    "kelas": "X.1 DIGITAL",
    "nohp": "+62 812-7555-4776",
    "mapel": "PJOK",
    "status": "Hadir",
    "jam": "07.20",
    "tgl": "21/7/2026"
  },
  {
    "id": 1784593254421,
    "nama": "Jihan Afifah",
    "kelas": "X.1 DIGITAL",
    "nohp": "+62 895-3623-89300",
    "mapel": "PJOK",
    "status": "Hadir",
    "jam": "07.20",
    "tgl": "21/7/2026"
  },
  {
    "id": 1784593257281,
    "nama": "Lailatul Salma",
    "kelas": "X.1 DIGITAL",
    "nohp": "+62 853-5501-8366",
    "mapel": "PJOK",
    "status": "Hadir",
    "jam": "07.20",
    "tgl": "21/7/2026"
  },
  {
    "id": 1784593236097,
    "nama": "Karen Trirely Gita Simatupang",
    "kelas": "X.1 DIGITAL",
    "nohp": "+62 821-5997-0950",
    "mapel": "PJOK",
    "status": "Hadir",
    "jam": "07.20",
    "tgl": "21/7/2026"
  },
  {
    "id": 1784593232732,
    "nama": "Aulia Anisa Putri",
    "kelas": "X.1 DIGITAL",
    "nohp": "+62 838-2604-8596",
    "mapel": "PJOK",
    "status": "Hadir",
    "jam": "07.20",
    "tgl": "21/7/2026"
  },
  {
    "id": 1784593230754,
    "nama": "Alika Kaysha Athalia",
    "kelas": "X.1 DIGITAL",
    "nohp": "+62 895-1857-9735",
    "mapel": "PJOK",
    "status": "Hadir",
    "jam": "07.20",
    "tgl": "21/7/2026"
  },
  {
    "id": 1784593228407,
    "nama": "Darrell Yusuf Athila",
    "kelas": "X.1 DIGITAL",
    "nohp": "-",
    "mapel": "PJOK",
    "status": "Hadir",
    "jam": "07.20",
    "tgl": "21/7/2026"
  },
  {
    "id": 1784593226161,
    "nama": "Fabyola Safitri",
    "kelas": "X.1 DIGITAL",
    "nohp": "+62 878-1154-6321",
    "mapel": "PJOK",
    "status": "Hadir",
    "jam": "07.20",
    "tgl": "21/7/2026"
  },
  {
    "id": 1784593224701,
    "nama": "Aimatul Chaira Syah",
    "kelas": "X.1 DIGITAL",
    "nohp": "+62 812-7709-1148",
    "mapel": "PJOK",
    "status": "Hadir",
    "jam": "07.20",
    "tgl": "21/7/2026"
  },
  {
    "id": 1784593219667,
    "nama": "Ahmad Syauqi Awinza",
    "kelas": "X.1 DIGITAL",
    "nohp": "+62 838-6775-9688",
    "mapel": "PJOK",
    "status": "Hadir",
    "jam": "07.20",
    "tgl": "21/7/2026"
  },
  {
    "id": 1784593217431,
    "nama": "Alfatihatunnisa Brilliant Ghaisa",
    "kelas": "X.1 DIGITAL",
    "nohp": "+62 838-7005-4050",
    "mapel": "PJOK",
    "status": "Hadir",
    "jam": "07.20",
    "tgl": "21/7/2026"
  },
  {
    "id": 1784593214991,
    "nama": "Alicia Queenara",
    "kelas": "X.1 DIGITAL",
    "nohp": "+62 821-7089-9030",
    "mapel": "PJOK",
    "status": "Hadir",
    "jam": "07.20",
    "tgl": "21/7/2026"
  },
  {
    "id": 1784593280471,
    "nama": "Razqa Fazil Defandryan Zack",
    "kelas": "X.1 DIGITAL",
    "nohp": "+48 666 666 672",
    "mapel": "PJOK",
    "status": "Hadir",
    "jam": "07.21",
    "tgl": "21/7/2026"
  },
  {
    "id": 1784592621241,
    "nama": "Darrell Yusuf Athila",
    "kelas": "X.1 DIGITAL",
    "nohp": "+62 812-6810-404",
    "mapel": "B. INGGRIS & SASTRA",
    "status": "Hadir",
    "jam": "07.10",
    "tgl": "21/7/2026"
  },
  {
    "id": 1784592615975,
    "nama": "Ahmad Syauqi Awinza",
    "kelas": "X.1 DIGITAL",
    "nohp": "+62 838-6775-9688",
    "mapel": "B. INGGRIS & SASTRA",
    "status": "Hadir",
    "jam": "07.10",
    "tgl": "21/7/2026"
  },
  {
    "id": 1784592610901,
    "nama": "Rakha Dwinanda Putra",
    "kelas": "X.1 DIGITAL",
    "nohp": "+62 821-7152-8540",
    "mapel": "B. INGGRIS & SASTRA",
    "status": "Hadir",
    "jam": "07.10",
    "tgl": "21/7/2026"
  },
  {
    "id": 1784592603052,
    "nama": "Zheno Alfares",
    "kelas": "X.1 DIGITAL",
    "nohp": "+62 822-8498-3746",
    "mapel": "B. INGGRIS & SASTRA",
    "status": "Hadir",
    "jam": "07.10",
    "tgl": "21/7/2026"
  },
  {
    "id": 1784592599030,
    "nama": "Muhammad Ibnu Syabil",
    "kelas": "X.1 DIGITAL",
    "nohp": "+62 813-7884-8072",
    "mapel": "B. INGGRIS & SASTRA",
    "status": "Hadir",
    "jam": "07.09",
    "tgl": "21/7/2026"
  },
  {
    "id": 1784592595028,
    "nama": "Synneva Adhwaretha",
    "kelas": "X.1 DIGITAL",
    "nohp": "+62 813-3442-3333",
    "mapel": "B. INGGRIS & SASTRA",
    "status": "Hadir",
    "jam": "07.09",
    "tgl": "21/7/2026"
  },
  {
    "id": 1784592586846,
    "nama": "Keisha Raina Rahman",
    "kelas": "X.1 DIGITAL",
    "nohp": "+62 812-7473-4591",
    "mapel": "B. INGGRIS & SASTRA",
    "status": "Hadir",
    "jam": "07.09",
    "tgl": "21/7/2026"
  },
  {
    "id": 1784592583241,
    "nama": "Lakeysha Aura Rezki",
    "kelas": "X.1 DIGITAL",
    "nohp": "+62 812-7555-4776",
    "mapel": "B. INGGRIS & SASTRA",
    "status": "Hadir",
    "jam": "07.09",
    "tgl": "21/7/2026"
  },
  {
    "id": 1784592580512,
    "nama": "Muhammad Sazlan Shah",
    "kelas": "X.1 DIGITAL",
    "nohp": "+62 895-3289-63535",
    "mapel": "B. INGGRIS & SASTRA",
    "status": "Hadir",
    "jam": "07.09",
    "tgl": "21/7/2026"
  },
  {
    "id": 1784592575050,
    "nama": "Alfatihatunnisa Brilliant Ghaisani",
    "kelas": "X.1 DIGITAL",
    "nohp": "+62 838-7005-4050",
    "mapel": "B. INGGRIS & SASTRA",
    "status": "Hadir",
    "jam": "07.09",
    "tgl": "21/7/2026"
  },
  {
    "id": 1784592571623,
    "nama": "Rahmad Ghatfan",
    "kelas": "X.1 DIGITAL",
    "nohp": "+62 857-6330-4596",
    "mapel": "B. INGGRIS & SASTRA",
    "status": "Hadir",
    "jam": "07.09",
    "tgl": "21/7/2026"
  },
  {
    "id": 1784592565555,
    "nama": "Aulia Anisa Putri",
    "kelas": "X.1 DIGITAL",
    "nohp": "+62 838-2604-8596",
    "mapel": "B. INGGRIS & SASTRA",
    "status": "Hadir",
    "jam": "07.09",
    "tgl": "21/7/2026"
  },
  {
    "id": 1784592561431,
    "nama": "Farrel Alvaro Laksamana",
    "kelas": "X.1 DIGITAL",
    "nohp": "+62 877-1121-8213",
    "mapel": "B. INGGRIS & SASTRA",
    "status": "Hadir",
    "jam": "07.09",
    "tgl": "21/7/2026"
  },
  {
    "id": 1784592556426,
    "nama": "Jamillatul Lathifah",
    "kelas": "X.1 DIGITAL",
    "nohp": "+62 821-7070-4249",
    "mapel": "B. INGGRIS & SASTRA",
    "status": "Hadir",
    "jam": "07.09",
    "tgl": "21/7/2026"
  },
  {
    "id": 1784592551208,
    "nama": "Rahma Andini Soraya",
    "kelas": "X.1 DIGITAL",
    "nohp": "+62 831-6113-9346",
    "mapel": "B. INGGRIS & SASTRA",
    "status": "Hadir",
    "jam": "07.09",
    "tgl": "21/7/2026"
  },
  {
    "id": 1784592548082,
    "nama": "Syauqi  Addawi",
    "kelas": "X.1 DIGITAL",
    "nohp": "+62 821-7041-8300",
    "mapel": "B. INGGRIS & SASTRA",
    "status": "Hadir",
    "jam": "07.09",
    "tgl": "21/7/2026"
  },
  {
    "id": 1784592542705,
    "nama": "Alicia Queenara",
    "kelas": "X.1 DIGITAL",
    "nohp": "+62 821-7089-9030",
    "mapel": "B. INGGRIS & SASTRA",
    "status": "Hadir",
    "jam": "07.09",
    "tgl": "21/7/2026"
  },
  {
    "id": 1784592538914,
    "nama": "Farel Aufa Deza",
    "kelas": "X.1 DIGITAL",
    "nohp": "+62 812-7607-7612",
    "mapel": "B. INGGRIS & SASTRA",
    "status": "Hadir",
    "jam": "07.08",
    "tgl": "21/7/2026"
  },
  {
    "id": 1784592536047,
    "nama": "Zahwa Alya putri",
    "kelas": "X.1 DIGITAL",
    "nohp": "+62 853-2000-7930",
    "mapel": "B. INGGRIS & SASTRA",
    "status": "Hadir",
    "jam": "07.08",
    "tgl": "21/7/2026"
  },
  {
    "id": 1784592531229,
    "nama": "Nashita Naura",
    "kelas": "X.1 DIGITAL",
    "nohp": "+62 812-7722-0850",
    "mapel": "B. INGGRIS & SASTRA",
    "status": "Hadir",
    "jam": "07.08",
    "tgl": "21/7/2026"
  },
  {
    "id": 1784592525550,
    "nama": "Alika Kaysha Athalia",
    "kelas": "X.1 DIGITAL",
    "nohp": "+62 895-1857-9735",
    "mapel": "B. INGGRIS & SASTRA",
    "status": "Hadir",
    "jam": "07.08",
    "tgl": "21/7/2026"
  },
  {
    "id": 1784592522762,
    "nama": "Taufiq Muhammad Rafi",
    "kelas": "X.1 DIGITAL",
    "nohp": "+62 895-4025-25533",
    "mapel": "B. INGGRIS & SASTRA",
    "status": "Hadir",
    "jam": "07.08",
    "tgl": "21/7/2026"
  },
  {
    "id": 1784592518747,
    "nama": "Luthfi Karim",
    "kelas": "X.1 DIGITAL",
    "nohp": "+62 822-8991-3571",
    "mapel": "B. INGGRIS & SASTRA",
    "status": "Hadir",
    "jam": "07.08",
    "tgl": "21/7/2026"
  },
  {
    "id": 1784592513866,
    "nama": "Muhammad Al Akram Boer",
    "kelas": "X.1 DIGITAL",
    "nohp": "+62 896-7941-8538",
    "mapel": "B. INGGRIS & SASTRA",
    "status": "Hadir",
    "jam": "07.08",
    "tgl": "21/7/2026"
  },
  {
    "id": 1784592506168,
    "nama": "Karen Trirely Gita Simatupang",
    "kelas": "X.1 DIGITAL",
    "nohp": "+62 821-5997-0950",
    "mapel": "B. INGGRIS & SASTRA",
    "status": "Hadir",
    "jam": "07.08",
    "tgl": "21/7/2026"
  },
  {
    "id": 1784592489343,
    "nama": "Aimatul Chaira Syah",
    "kelas": "X.1 DIGITAL",
    "nohp": "+62 812-7709-1148",
    "mapel": "B. INGGRIS & SASTRA",
    "status": "Hadir",
    "jam": "07.08",
    "tgl": "21/7/2026"
  },
  {
    "id": 1784592485451,
    "nama": "Rivana Azzahra",
    "kelas": "X.1 DIGITAL",
    "nohp": "+62 812-2908-5724",
    "mapel": "B. INGGRIS & SASTRA",
    "status": "Hadir",
    "jam": "07.08",
    "tgl": "21/7/2026"
  },
  {
    "id": 1784592480295,
    "nama": "Jihan Afifah",
    "kelas": "X.1 DIGITAL",
    "nohp": "+62 895-3623-89300",
    "mapel": "B. INGGRIS & SASTRA",
    "status": "Hadir",
    "jam": "07.08",
    "tgl": "21/7/2026"
  },
  {
    "id": 1784592472746,
    "nama": "Lailatul Salma",
    "kelas": "X.1 DIGITAL",
    "nohp": "+62 853-5501-8366",
    "mapel": "B. INGGRIS & SASTRA",
    "status": "Hadir",
    "jam": "07.07",
    "tgl": "21/7/2026"
  },
  {
    "id": 1784592468449,
    "nama": "Sabrina Arif Rayyani",
    "kelas": "X.1 DIGITAL",
    "nohp": "+62 853-5501-9199",
    "mapel": "B. INGGRIS & SASTRA",
    "status": "Hadir",
    "jam": "07.07",
    "tgl": "21/7/2026"
  },
  {
    "id": 1784592463923,
    "nama": "Atika Najwa Ikhwani",
    "kelas": "X.1 DIGITAL",
    "nohp": "+62 877-0928-7343",
    "mapel": "B. INGGRIS & SASTRA",
    "status": "Hadir",
    "jam": "07.07",
    "tgl": "21/7/2026"
  },
  {
    "id": 1784592458353,
    "nama": "Khaira Sachi Kayana",
    "kelas": "X.1 DIGITAL",
    "nohp": "+62 821-7002-0056",
    "mapel": "B. INGGRIS & SASTRA",
    "status": "Hadir",
    "jam": "07.07",
    "tgl": "21/7/2026"
  },
  {
    "id": 1784592451884,
    "nama": "Fabyola Safitri",
    "kelas": "X.1 DIGITAL",
    "nohp": "+62 878-1154-6321",
    "mapel": "B. INGGRIS & SASTRA",
    "status": "Hadir",
    "jam": "07.07",
    "tgl": "21/7/2026"
  },
  {
    "id": 1784592439065,
    "nama": "Arum Mustifa",
    "kelas": "X.1 DIGITAL",
    "nohp": "+62 831-8751-2604",
    "mapel": "B. INGGRIS & SASTRA",
    "status": "Hadir",
    "jam": "07.07",
    "tgl": "21/7/2026"
  }
]